object_detection/__init__.py
object_detection/eval_util.py
object_detection/eval_util_test.py
object_detection/export_inference_graph.py
object_detection/export_tflite_graph_lib_tf2.py
object_detection/export_tflite_graph_lib_tf2_test.py
object_detection/export_tflite_graph_tf2.py
object_detection/export_tflite_ssd_graph.py
object_detection/export_tflite_ssd_graph_lib.py
object_detection/export_tflite_ssd_graph_lib_tf1_test.py
object_detection/exporter.py
object_detection/exporter_lib_tf2_test.py
object_detection/exporter_lib_v2.py
object_detection/exporter_main_v2.py
object_detection/exporter_tf1_test.py
object_detection/inputs.py
object_detection/inputs_test.py
object_detection/model_hparams.py
object_detection/model_lib.py
object_detection/model_lib_tf1_test.py
object_detection/model_lib_tf2_test.py
object_detection/model_lib_v2.py
object_detection/model_main.py
object_detection/model_main_tf2.py
object_detection/model_tpu_main.py
object_detection/anchor_generators/__init__.py
object_detection/anchor_generators/flexible_grid_anchor_generator.py
object_detection/anchor_generators/flexible_grid_anchor_generator_test.py
object_detection/anchor_generators/grid_anchor_generator.py
object_detection/anchor_generators/grid_anchor_generator_test.py
object_detection/anchor_generators/multiple_grid_anchor_generator.py
object_detection/anchor_generators/multiple_grid_anchor_generator_test.py
object_detection/anchor_generators/multiscale_grid_anchor_generator.py
object_detection/anchor_generators/multiscale_grid_anchor_generator_test.py
object_detection/box_coders/__init__.py
object_detection/box_coders/faster_rcnn_box_coder.py
object_detection/box_coders/faster_rcnn_box_coder_test.py
object_detection/box_coders/keypoint_box_coder.py
object_detection/box_coders/keypoint_box_coder_test.py
object_detection/box_coders/mean_stddev_box_coder.py
object_detection/box_coders/mean_stddev_box_coder_test.py
object_detection/box_coders/square_box_coder.py
ctg_object_detection_tools-0.0.1.dist-info/LICENSE
ctg_object_detection_tools-0.0.1.dist-info/METADATA
ctg_object_detection_tools-0.0.1.dist-info/WHEEL
ctg_object_detection_tools-0.0.1.dist-info/top_level.txt
ctg_object_detection_tools-0.0.1.dist-info/RECORD
