Metadata-Version: 2.1
Name: ctg-object-detection-tools
Version: 0.0.1
Summary: Tensorflow CTG Object Detection Library
Home-page: https://github.com/tensorflow
Author: TF
Author-email: github-admin@tensorflow.org
Project-URL: Bug Tracker, https://github.com/tensorflow/issues
Classifier: Programming Language :: Python :: 3
Classifier: License :: OSI Approved :: MIT License
Classifier: Operating System :: OS Independent
Requires-Python: >=3.6
License-File: LICENSE
